README.md
setup.py
zim2txt/__init__.py
zim2txt/main.py
zim2txt.egg-info/PKG-INFO
zim2txt.egg-info/SOURCES.txt
zim2txt.egg-info/dependency_links.txt
zim2txt.egg-info/requires.txt
zim2txt.egg-info/top_level.txt