Metadata-Version: 2.1
Name: zim2txt
Version: 1.0.0
Summary: A simple tool to extract articles from a .zim file into .txt files.
Author: Mehmet Utku OZTURK
Author-email: <contact@ælphard.tk>
Keywords: zim,wikipedia,txt
Classifier: Development Status :: 3 - Alpha
Classifier: Intended Audience :: Developers
Classifier: Natural Language :: English
Classifier: Programming Language :: Python :: 3
